Workbook
Name Срез_Месяц: #N/A

Sheet Данные
A1: Данные за Q1 2026
A2: Дата | B2: Продукт | C2: Категория | D2: Регион | E2: Объем (уп) | F2: Цена | G2: Себестоимость | H2: Выручка | I2: Маржа | J2: Месяц
A3: 21.02.2026 | B3: KitKat | C3: Шоколад | D3: Россия | E3: 495 | F3: 80 | G3: 48 | H3: 39600 | I3: 15840 | J3: =TEXT(A3,"ММММ") -> Февраль
A4: 15.01.2026 | B4: Nescafe | C4: Кофе | D4: Россия | E4: 498 | F4: 250 | G4: 150 | H4: 124500 | I4: 49800 | J4: =TEXT(A4,"ММММ") -> Январь
A5: 01.03.2026 | B5: Nido | C5: Молоко | D5: Россия | E5: 484 | F5: 300 | G5: 180 | H5: 145200 | I5: 58080 | J5: =TEXT(A5,"ММММ") -> Март
A6: 03.03.2026 | B6: Nescafe | C6: Кофе | D6: Россия | E6: 447 | F6: 250 | G6: 150 | H6: 111750 | I6: 44700 | J6: =TEXT(A6,"ММММ") -> Март
A7: 21.01.2026 | B7: KitKat | C7: Шоколад | D7: Казахстан | E7: 83 | F7: 80 | G7: 48 | H7: 6640 | I7: 2656 | J7: =TEXT(A7,"ММММ") -> Январь
A8: 13.03.2026 | B8: Nescafe | C8: Кофе | D8: Россия | E8: 418 | F8: 250 | G8: 150 | H8: 104500 | I8: 41800 | J8: =TEXT(A8,"ММММ") -> Март
A9: 12.03.2026 | B9: Nescafe | C9: Кофе | D9: Узбекистан | E9: 414 | F9: 250 | G9: 150 | H9: 103500 | I9: 41400 | J9: =TEXT(A9,"ММММ") -> Март
A10: 30.03.2026 | B10: Nescafe | C10: Кофе | D10: Узбекистан | E10: 396 | F10: 250 | G10: 150 | H10: 99000 | I10: 39600 | J10: =TEXT(A10,"ММММ") -> Март
A11: 22.03.2026 | B11: Nescafe | C11: Кофе | D11: Казахстан | E11: 366 | F11: 250 | G11: 150 | H11: 91500 | I11: 36600 | J11: =TEXT(A11,"ММММ") -> Март
A12: 17.03.2026 | B12: Nido | C12: Молоко | D12: Россия | E12: 300 | F12: 300 | G12: 180 | H12: 90000 | I12: 36000 | J12: =TEXT(A12,"ММММ") -> Март
A13: 24.01.2026 | B13: Nescafe | C13: Кофе | D13: Украина | E13: 299 | F13: 250 | G13: 150 | H13: 74750 | I13: 29900 | J13: =TEXT(A13,"ММММ") -> Январь
A14: 03.01.2026 | B14: KitKat | C14: Шоколад | D14: Россия | E14: 211 | F14: 80 | G14: 48 | H14: 16880 | I14: 6752 | J14: =TEXT(A14,"ММММ") -> Январь
... A202: 08.02.2026 | B202: KitKat | C202: Шоколад | D202: Казахстан | E202: 160 | F202: 80 | G202: 48 | H202: 12800 | I202: 5120 | J202: =TEXT(A202,"ММММ") -> Февраль

Sheet План на квартал
A1: Продукт | B1: План Q1 2026 (руб) | C1: % от плана
A2: Nescafe | B2: 3500000 | C2: 0.42
A3: KitKat | B3: 2500000 | C3: 0.3
A4: Maggi | B4: 1200000 | C4: 0.14
A5: Nido | B5: 800000 | C5: 0.1
A6: Несквик | B6: 300000 | C6: 0.04
A7: Всего СНГ | B7: 8300000 | C7: 1

Sheet План-Факт
A1: Продукт | B1: План | C1: Факт | D1: Отклонение | E1: %
A2: Nescafe | B2: =VLOOKUP(A2,'План на квартал'!$A$1:$B$7,2,0) -> 3500000 | C2: =SUMIF(Данные!B:B,A2,Данные!H:H) -> 5446000 | D2: =C2-B2 -> 1946000 | E2: =C2/B2 -> 1.556
A3: KitKat | B3: =VLOOKUP(A3,'План на квартал'!$A$1:$B$7,2,0) -> 2500000 | C3: =SUMIF(Данные!B:B,A3,Данные!H:H) -> 1080320 | D3: =C3-B3 -> -1419680 | E3: =C3/B3 -> 0.432128
A4: Maggi | B4: =VLOOKUP(A4,'План на квартал'!$A$1:$B$7,2,0) -> 1200000 | C4: =SUMIF(Данные!B:B,A4,Данные!H:H) -> 978000 | D4: =C4-B4 -> -222000 | E4: =C4/B4 -> 0.815
A5: Nido | B5: =VLOOKUP(A5,'План на квартал'!$A$1:$B$7,2,0) -> 800000 | C5: =SUMIF(Данные!B:B,A5,Данные!H:H) -> 1346100 | D5: =C5-B5 -> 546100 | E5: =C5/B5 -> 1.682625
A6: Несквик | B6: =VLOOKUP(A6,'План на квартал'!$A$1:$B$7,2,0) -> 300000 | C6: =SUMIF(Данные!B:B,A6,Данные!H:H) -> 718050 | D6: =C6-B6 -> 418050 | E6: =C6/B6 -> 2.3935
A7: Всего СНГ | B7: =VLOOKUP(A7,'План на квартал'!$A$1:$B$7,2,0) -> 8300000 | C7: =SUM(C2:C6) -> 9568470 | D7: =C7-B7 -> 1268470 | E7: =C7/B7 -> 1.1528277

Sheet Сводные
A1: Месяц | B1: (Все) | D1: Топ-регион
A2: Регион | B2: (Все) | D2: Регион | E2: Сумма по полю Выручка
D3: Казахстан | E3: 1101510
A4: Продукт | B4: Сумма по полю Выручка | D4: Украина | E4: 1192240
A5: Несквик | B5: 718050 | D5: Беларусь | E5: 1260280
A6: Maggi | B6: 978000 | D6: Узбекистан | E6: 1686250
A7: KitKat | B7: 1080320 | D7: Россия | E7: 4328190
A8: Nido | B8: 1346100 | D8: Общий итог | E8: 9568470
A9: Nescafe | B9: 5446000
A10: Общий итог | B10: 9568470

Sheet Дашборд
A1: 🏆 Анализ продаж Mestle СНГ | Q1 2026
A2: 📊 Общая выручка | D2: 🔝 Лучший регион по выручке | F2: 🔝 Топ-продукт
A3: Факт | B3: =SUM(Данные!H:H) -> 9568470 | D3: {=INDEX(Сводные!D3:D7, MATCH(MAX(Сводные!E3:E7),Сводные!E3:E7),0)} -> Россия | F3: =INDEX(Сводные!A5:A19, MATCH(MAX(Сводные!B5:B9),Сводные!B5:B9,0)) -> Nescafe
A4: План | B4: ='План на квартал'!B7 -> 8300000
A5: 📈 | B5: =B3/VLOOKUP("Всего СНГ",'План на квартал'!A:B,2,0)-1 -> 0.15282771
